Metadata-Version: 1.1
Name: draw-devops-against-humanity
Version: 0.0.3
Summary: Draw devops against humanity sentence.
Home-page: https://github.com/lenarother/draw-devops-against-humanity/
Author: Magdalena Rother
Author-email: rother.magdalena@gmail.com
License: MIT
Keywords: devops against humanity,cards against humanity
Platform: UNKNOWN
Classifier: Development Status :: 3 - Alpha
Classifier: Intended Audience :: Developers
Classifier: License :: OSI Approved :: Apache Software License
Classifier: Operating System :: OS Independent
Classifier: Programming Language :: Python
Classifier: Programming Language :: Python :: 2
Classifier: Programming Language :: Python :: 2.7
Classifier: Programming Language :: Python :: 3
Classifier: Programming Language :: Python :: 3.4
Classifier: Programming Language :: Python :: 3.5
